LICENSE
MANIFEST.in
README.md
requirements.txt
setup.py
src/pii_transform/__init__.py
src/pii_transform/defs.py
src/pii_transform.egg-info/PKG-INFO
src/pii_transform.egg-info/SOURCES.txt
src/pii_transform.egg-info/dependency_links.txt
src/pii_transform.egg-info/entry_points.txt
src/pii_transform.egg-info/requires.txt
src/pii_transform.egg-info/top_level.txt
src/pii_transform/api/__init__.py
src/pii_transform/api/e2e.py
src/pii_transform/api/transform.py
src/pii_transform/app/__init__.py
src/pii_transform/app/chunk.py
src/pii_transform/app/transform.py
src/pii_transform/helper/__init__.py
src/pii_transform/helper/misc.py
src/pii_transform/helper/placeholder.py
src/pii_transform/helper/substitution.py
src/pii_transform/helper/synthetic.py
src/pii_transform/out/__init__.py
src/pii_transform/out/csv.py
src/pii_transform/out/docwriter.py
src/pii_transform/resources/placeholder.json
src/pii_transform/resources/transform.json