Metadata-Version: 2.1
Name: pii-transform
Version: 0.7.0
Summary: Transform recognized PII instances in a document
Home-page: https://github.com/piisa/pii-transform
Download-URL: https://github.com/piisa/pii-transform/tarball/v0.7.0
Author: Paulo Villegas
Author-email: paulo.vllgs@gmail.com
License: Apache
Keywords: PIISA, PII
Classifier: Programming Language :: Python :: 3 :: Only
Classifier: License :: OSI Approved :: Apache Software License
Classifier: Development Status :: 4 - Beta
Classifier: Topic :: Software Development :: Libraries :: Application Frameworks
Requires-Python: >=3.8
Provides-Extra: test
Provides-Extra: e2e
License-File: LICENSE
